setup.py
parse_args/__init__.py
parse_args.egg-info/PKG-INFO
parse_args.egg-info/SOURCES.txt
parse_args.egg-info/dependency_links.txt
parse_args.egg-info/top_level.txt