Metadata-Version: 2.1
Name: parse-args
Version: 2.0.0
Summary: Parse Command Line Arguments From String
Home-page: UNKNOWN
Author: Pixelsuft
License: MIT
Keywords: parse_args
Platform: UNKNOWN
Classifier: Programming Language :: Python :: 3
Classifier: License :: OSI Approved :: MIT License
Requires-Python: >=3.5
